tp_helper/__init__.py
tp_helper/base_items/base_discord.py
tp_helper/base_items/base_logging_service.py
tp_helper/base_items/base_request.py
tp_helper/base_items/base_response.py
tp_helper/base_items/base_schema.py
tp_helper/base_items/base_timestamp_model.py
tp_helper/base_items/base_worker.py
tp_helper/base_items/base_worker_service.py
tp_helper/base_queues/base_ack_list_queue_repo.py
tp_helper/base_queues/base_fast_queue_repo.py
tp_helper/base_queues/base_idle_queue_repo.py
tp_helper/base_queues/base_queue_repo.py
tp_helper/base_queues/base_repo.py
tp_helper/base_queues/base_stream_queue_repo.py
tp_helper/base_repos/base_db_repo.py
tp_helper/base_repos/base_redis_repo.py
tp_helper/decorators/decorator_retry_forever.py
tp_helper/discord_helper.py
tp_helper/functions.py
tp_helper/proxy_manager_helper/__init__.py
tp_helper/proxy_manager_helper/proxy_manager_helper.py
tp_helper/proxy_manager_helper/schemas/__init__.py
tp_helper/proxy_manager_helper/schemas/proxy_schema.py
tp_helper/redis_helper.py
tp_helper/repository_manager_helper.py
tp_helper/revolt_helper.py
tp_helper/session_manager_helper.py
tp_helper/types/null_filter_type.py
tp_helper/types/sort_order_type.py
tp_helper/validate_subsets.py
tp_helper-0.4.86.dist-info/METADATA
tp_helper-0.4.86.dist-info/WHEEL
tp_helper-0.4.86.dist-info/RECORD
