Metadata-Version: 2.3
Name: tp-helper
Version: 0.4.86
Summary: 
Author: TP
Author-email: tp@tp.com
Requires-Python: >=3.12
Classifier: Programming Language :: Python :: 3
Classifier: Programming Language :: Python :: 3.12
Classifier: Programming Language :: Python :: 3.13
Requires-Dist: aiohttp (>=3.13.2)
Requires-Dist: dotenv (>=0.9.9,<0.10.0)
Requires-Dist: load-dotenv (>=0.1.0,<0.2.0)
Requires-Dist: lxml (>=6.0.1,<7.0.0)
Requires-Dist: pydantic (>=2.10.6,<3.0.0)
Requires-Dist: python-json-logger (>=4.0.0,<5.0.0)
Requires-Dist: python-logging-loki-v2 (>=0.4.4,<0.5.0)
Requires-Dist: redis (>=7.1.0)
Requires-Dist: requests (>=2.32.5,<3.0.0)
Requires-Dist: sqlalchemy (>=2.0.38,<3.0.0)
